dcm_processor/__init__.py
dcm_processor/argparser.py
dcm_processor/files.py
dcm_processor/script.py
dcm_processor/worker.py
dcm_processor/services/base/module/requirements.txt
dcm_processor/services/base/module/script.sh
dcm_processor/services/base/module/DicomAnonymizerService/CTP.jar
dcm_processor/services/base/module/DicomAnonymizerService/DAT.jar
dcm_processor/services/base/module/DicomAnonymizerService/__init__.py
dcm_processor/services/base/module/DicomAnonymizerService/anonymize.py
dcm_processor/services/base/module/DicomAnonymizerService/clibwrapper_jiio-1.2-pre-dr-b04.jar
dcm_processor/services/base/module/DicomAnonymizerService/dcm4che-imageio-rle-2.0.25.jar
dcm_processor/services/base/module/DicomAnonymizerService/dcm4che.jar
dcm_processor/services/base/module/DicomAnonymizerService/fhir_lib.py
dcm_processor/services/base/module/DicomAnonymizerService/jai_imageio-1.2-pre-dr-b04.jar
dcm_processor/services/base/module/DicomAnonymizerService/log4j.jar
dcm_processor/services/base/module/DicomAnonymizerService/pixelmed_codec.jar
dcm_processor/services/base/module/DicomAnonymizerService/util.jar
dcm_processor/services/base/module/DicomAnonymizerService/utils.py
dcm_processor/services/base/module/DicomAnonymizerService/config/dicom-anonymizer.script
dcm_processor/services/base/module/DicomAnonymizerService/config/hash_table.csv
dcm_processor/services/base/module/DicomAnonymizerService/config/psudonyms.csv
dcm_processor/services/base/module/storageManager/__init__.py
dcm_processor/services/base/module/storageManager/header_codes.json
dcm_processor/services/base/module/storageManager/lib.py
dcm_processor/services/base/module/storageManager/main.py
dcm_processor/services/base/module/systemcleaner/__init__.py
dcm_processor/services/base/module/systemcleaner/main.py
dcm_processor/services/base/registry/__init__.py
dcm_processor/services/dcm2nii/module/__init__.py
dcm_processor/services/dcm2nii/module/dcm2niix
dcm_processor/services/dcm2nii/module/lib.py
dcm_processor-1.1.6.dist-info/LICENSE
dcm_processor-1.1.6.dist-info/METADATA
dcm_processor-1.1.6.dist-info/WHEEL
dcm_processor-1.1.6.dist-info/entry_points.txt
dcm_processor-1.1.6.dist-info/top_level.txt
dcm_processor-1.1.6.dist-info/RECORD
