Metadata-Version: 2.1
Name: dcm-processor
Version: 1.1.6
Summary: A Command line tool for the dicom processor library
Home-page: https://github.com/giesekow/dcm-processor-cli
Author: Giles Tetteh
Author-email: giles.tetteh@tum.de
License: UNKNOWN
Keywords: orthanc,dicom,worker,processor,translation,medical
Platform: UNKNOWN
Classifier: Programming Language :: Python :: 3
Classifier: License :: OSI Approved :: MIT License
Classifier: Operating System :: OS Independent
License-File: LICENSE
Requires-Dist: GitPython (==3.1.45)
Requires-Dist: PyYAML (==6.0.2)
Requires-Dist: inquirer (==2.5.0)
Requires-Dist: python-dotenv (==1.1.1)
Requires-Dist: requests (==2.32.4)
Requires-Dist: ruamel-yaml (==0.18.14)
